stream_parser/__init__.py
stream_parser/chunked.py
stream_parser/parser.py
stream_parser-0.1.0.dist-info/METADATA
stream_parser-0.1.0.dist-info/WHEEL
stream_parser-0.1.0.dist-info/top_level.txt
stream_parser-0.1.0.dist-info/RECORD
