Metadata-Version: 2.1
Name: stream-parser
Version: 0.1.0
Summary: package_description
Author-email: Marcel Claramunt <marcel@moveread.com>
Project-URL: repo, https://github.com/moveread/REPO.git
Requires-Python: >=3.10
